geocoding_api_extract/__init__.py
geocoding_api_extract/utils/__init__.py
geocoding_api_extract/utils/progress.py
geocoding_api_extract-0.0.2.dist-info/LICENSE
geocoding_api_extract-0.0.2.dist-info/METADATA
geocoding_api_extract-0.0.2.dist-info/WHEEL
geocoding_api_extract-0.0.2.dist-info/top_level.txt
geocoding_api_extract-0.0.2.dist-info/RECORD
