Metadata-Version: 2.1
Name: geocoding-api-extract
Version: 0.0.2
Summary: Geocoding api extract to dataframe script.
Home-page: https://github.com/AndoKalrisian/geocoding_api_extract
Author: Anders Bergman
Author-email: 
License: MIT License
Platform: UNKNOWN
Classifier: Programming Language :: Python :: 3
Classifier: License :: OSI Approved :: MIT License
Classifier: Operating System :: OS Independent
Requires-Python: >=3.6
Requires-Dist: pandas
Requires-Dist: numpy
Requires-Dist: configparser
